<?xml version="1.0" encoding="utf-8"?><index><stem n="locat"><phr n="locations"><ent r="3" t="1" w="35" /><ent r="3" t="1" w="35" /><ent r="1000" t="1043" w="4" /><ent r="1000" t="1043" w="4" /><ent r="106" t="1043" w="12" /><ent r="106" t="1043" w="12" /><ent r="1000" t="1063" w="4" /><ent r="1000" t="1063" w="4" /><ent r="106" t="1063" w="12" /><ent r="106" t="1063" w="12" /><ent r="68" t="1081" w="131" /><ent r="68" t="1081" w="131" /></phr><phr n="Location"><ent r="8" t="7" w="821" /><ent r="8" t="7" w="821" /><ent r="8" t="341" w="77" /><ent r="8" t="341" w="77" /><ent r="1000" t="342" w="2" /><ent r="1000" t="342" w="2" /><ent r="106" t="342" w="5" /><ent r="106" t="342" w="5" /><ent r="1000" t="487" w="2" /><ent r="1000" t="487" w="2" /><ent r="106" t="487" w="5" /><ent r="106" t="487" w="5" /><ent r="8" t="807" w="26" /><ent r="8" t="807" w="26" /><ent r="8" t="808" w="26" /><ent r="8" t="808" w="26" /><ent r="8" t="809" w="29" /><ent r="8" t="809" w="29" /><ent r="8" t="810" w="28" /><ent r="8" t="810" w="28" /><ent r="8" t="881" w="35" /><ent r="8" t="881" w="35" /><ent r="8" t="882" w="35" /><ent r="8" t="882" w="35" /><ent r="8" t="883" w="34" /><ent r="8" t="883" w="34" /><ent r="8" t="884" w="35" /><ent r="8" t="884" w="35" /><ent r="8" t="885" w="34" /><ent r="8" t="885" w="34" /><ent r="8" t="886" w="34" /><ent r="8" t="886" w="34" /><ent r="8" t="888" w="37" /><ent r="8" t="888" w="37" /><ent r="8" t="889" w="34" /><ent r="8" t="889" w="34" /><ent r="1000" t="1055" w="3" /><ent r="1000" t="1055" w="3" /><ent r="106" t="1055" w="7" /><ent r="106" t="1055" w="7" /><ent r="1000" t="1058" w="3" /><ent r="1000" t="1058" w="3" /><ent r="106" t="1058" w="7" /><ent r="106" t="1058" w="7" /><ent r="1000" t="1060" w="4" /><ent r="1000" t="1060" w="4" /><ent r="106" t="1060" w="14" /><ent r="106" t="1060" w="14" /><ent r="8" t="1060" w="32" /><ent r="8" t="1060" w="32" /><ent r="68" t="1081" w="55" /><ent r="68" t="1081" w="55" /><ent r="68" t="1081" w="60" /><ent r="68" t="1081" w="60" /><ent r="68" t="1081" w="69" /><ent r="68" t="1081" w="69" /><ent r="68" t="1081" w="2624" /><ent r="68" t="1081" w="2624" /><ent r="64" t="1081" w="3110" /><ent r="64" t="1081" w="3110" /></phr><phr n="location"><ent r="7" t="83" w="30" /><ent r="7" t="83" w="30" /><ent r="7" t="328" w="46" /><ent r="7" t="328" w="46" /><ent r="7" t="335" w="12" /><ent r="7" t="335" w="12" /><ent r="7" t="341" w="59" /><ent r="7" t="341" w="59" /><ent r="7" t="541" w="49" /><ent r="7" t="541" w="82" /><ent r="7" t="541" w="82" /><ent r="7" t="622" w="57" /><ent r="7" t="698" w="51" /><ent r="7" t="698" w="84" /><ent r="7" t="698" w="84" /><ent r="7" t="926" w="46" /><ent r="7" t="926" w="46" /><ent r="7" t="1055" w="20" /><ent r="7" t="1055" w="20" /><ent r="3" t="1082" w="415" /><ent r="3" t="1082" w="415" /></phr><phr n="locate"><ent r="7" t="213" w="23" /><ent r="7" t="213" w="23" /><ent r="7" t="403" w="31" /><ent r="7" t="403" w="31" /><ent r="7" t="404" w="52" /><ent r="7" t="404" w="52" /><ent r="7" t="471" w="39" /><ent r="7" t="471" w="39" /><ent r="7" t="541" w="61" /><ent r="7" t="541" w="61" /><ent r="7" t="698" w="63" /><ent r="7" t="698" w="63" /><ent r="3" t="1082" w="470" /><ent r="3" t="1082" w="470" /></phr><phr n="located"><ent r="7" t="332" w="15" /><ent r="7" t="332" w="15" /><ent r="7" t="334" w="15" /><ent r="7" t="334" w="15" /><ent r="7" t="342" w="16" /><ent r="7" t="342" w="16" /><ent r="7" t="1033" w="22" /><ent r="7" t="1033" w="22" /><ent r="7" t="1060" w="40" /><ent r="3" t="1083" w="42" /><ent r="3" t="1083" w="42" /></phr><phr n="Locations"><ent r="3" t="1083" w="76" /><ent r="3" t="1083" w="76" /></phr></stem><stem n="within"><phr n="within"><ent r="3" t="1" w="36" /><ent r="3" t="1" w="36" /><ent r="6" t="4" w="77" /><ent r="6" t="4" w="77" /><ent r="6" t="4" w="84" /><ent r="6" t="4" w="84" /><ent r="6" t="4" w="99" /><ent r="6" t="4" w="99" /><ent r="6" t="4" w="206" /><ent r="6" t="4" w="206" /><ent r="6" t="4" w="265" /><ent r="6" t="4" w="265" /><ent r="6" t="7" w="648" /><ent r="6" t="7" w="648" /><ent r="6" t="7" w="1098" /><ent r="6" t="7" w="1098" /><ent r="6" t="8" w="300" /><ent r="6" t="8" w="300" /><ent r="6" t="8" w="430" /><ent r="6" t="8" w="430" /><ent r="6" t="8" w="605" /><ent r="6" t="8" w="605" /><ent r="7" t="94" w="21" /><ent r="7" t="94" w="21" /><ent r="7" t="332" w="16" /><ent r="7" t="332" w="16" /><ent r="7" t="334" w="16" /><ent r="7" t="334" w="16" /><ent r="7" t="335" w="16" /><ent r="7" t="335" w="16" /><ent r="7" t="342" w="17" /><ent r="7" t="342" w="17" /><ent r="7" t="434" w="25" /><ent r="7" t="434" w="25" /><ent r="7" t="491" w="17" /><ent r="7" t="491" w="17" /><ent r="7" t="615" w="32" /><ent r="7" t="615" w="32" /><ent r="7" t="630" w="41" /><ent r="7" t="630" w="41" /><ent r="7" t="824" w="122" /><ent r="7" t="824" w="122" /><ent r="7" t="852" w="29" /><ent r="7" t="852" w="29" /><ent r="7" t="992" w="91" /><ent r="7" t="992" w="91" /><ent r="7" t="1024" w="29" /><ent r="7" t="1024" w="29" /><ent r="7" t="1031" w="21" /><ent r="7" t="1031" w="21" /><ent r="7" t="1038" w="25" /><ent r="7" t="1038" w="25" /><ent r="3" t="1082" w="841" /><ent r="3" t="1082" w="841" /><ent r="3" t="1083" w="83" /><ent r="3" t="1083" w="83" /></phr><phr n="Within"><ent r="70" t="5" w="857" /><ent r="70" t="5" w="857" /><ent r="8" t="498" w="57" /><ent r="8" t="498" w="57" /></phr></stem><stem n="warehous"><phr n="warehouses"><ent r="3" t="1" w="37" /><ent r="3" t="1" w="37" /><ent r="9" t="341" w="105" /><ent r="9" t="341" w="105" /></phr><phr n="warehouse"><ent r="7" t="332" w="18" /><ent r="7" t="334" w="18" /><ent r="7" t="335" w="18" /><ent r="7" t="342" w="19" /><ent r="7" t="622" w="18" /><ent r="7" t="622" w="18" /><ent r="7" t="622" w="36" /><ent r="7" t="622" w="44" /><ent r="7" t="622" w="55" /></phr><phr n="Warehouse"><ent r="1000" t="341" w="1" /><ent r="1000" t="341" w="1" /><ent r="106" t="341" w="5" /><ent r="106" t="341" w="5" /><ent r="7" t="341" w="111" /><ent r="7" t="341" w="111" /><ent r="1000" t="342" w="1" /><ent r="1000" t="342" w="1" /><ent r="106" t="342" w="4" /><ent r="106" t="342" w="4" /><ent r="64" t="1081" w="3109" /><ent r="64" t="1081" w="3109" /></phr><phr n="Warehouses"><ent r="8" t="341" w="22" /><ent r="8" t="341" w="22" /><ent r="68" t="341" w="95" /><ent r="68" t="341" w="95" /><ent r="8" t="622" w="26" /><ent r="8" t="622" w="26" /></phr></stem><stem n="store"><phr n="stores"><ent r="3" t="1" w="39" /><ent r="7" t="133" w="21" /><ent r="7" t="133" w="21" /><ent r="7" t="138" w="23" /><ent r="7" t="138" w="23" /><ent r="7" t="142" w="29" /><ent r="7" t="142" w="29" /><ent r="7" t="144" w="29" /><ent r="7" t="144" w="29" /><ent r="7" t="147" w="41" /><ent r="7" t="147" w="41" /><ent r="7" t="148" w="40" /><ent r="7" t="165" w="23" /><ent r="7" t="165" w="23" /><ent r="7" t="171" w="20" /><ent r="7" t="171" w="20" /><ent r="7" t="172" w="25" /><ent r="7" t="172" w="25" /><ent r="7" t="173" w="23" /><ent r="7" t="173" w="23" /><ent r="7" t="174" w="23" /><ent r="7" t="174" w="23" /><ent r="7" t="534" w="16" /><ent r="7" t="534" w="16" /><ent r="7" t="540" w="16" /><ent r="7" t="540" w="16" /><ent r="7" t="621" w="33" /><ent r="7" t="621" w="33" /><ent r="7" t="668" w="34" /><ent r="7" t="668" w="34" /></phr><phr n="store"><ent r="8" t="2" w="35" /><ent r="6" t="2" w="177" /><ent r="6" t="3" w="16" /><ent r="6" t="3" w="16" /><ent r="147" t="3" w="35" /><ent r="147" t="3" w="99" /><ent r="6" t="3" w="206" /><ent r="6" t="3" w="221" /><ent r="6" t="4" w="46" /><ent r="6" t="4" w="46" /><ent r="6" t="4" w="102" /><ent r="6" t="4" w="105" /><ent r="6" t="4" w="105" /><ent r="6" t="5" w="631" /><ent r="5" t="6" w="1092" /><ent r="8" t="7" w="80" /><ent r="9" t="7" w="168" /><ent r="9" t="7" w="168" /><ent r="147" t="7" w="200" /><ent r="8" t="7" w="210" /><ent r="8" t="7" w="210" /><ent r="6" t="7" w="561" /><ent r="6" t="7" w="561" /><ent r="6" t="7" w="636" /><ent r="6" t="7" w="636" /><ent r="7" t="7" w="673" /><ent r="7" t="7" w="673" /><ent r="6" t="7" w="883" /><ent r="6" t="7" w="915" /><ent r="6" t="7" w="915" /><ent r="6" t="8" w="31" /><ent r="6" t="8" w="74" /><ent r="6" t="8" w="74" /><ent r="6" t="8" w="86" /><ent r="6" t="8" w="86" /><ent r="6" t="8" w="263" /><ent r="6" t="8" w="303" /><ent r="6" t="8" w="319" /><ent r="6" t="8" w="378" /><ent r="6" t="8" w="414" /><ent r="6" t="8" w="432" /><ent r="6" t="8" w="441" /><ent r="6" t="8" w="441" /><ent r="6" t="8" w="462" /><ent r="6" t="8" w="462" /><ent r="6" t="8" w="506" /><ent r="6" t="8" w="506" /><ent r="6" t="8" w="534" /><ent r="6" t="8" w="542" /><ent r="6" t="8" w="556" /><ent r="6" t="8" w="583" /><ent r="6" t="8" w="583" /><ent r="6" t="8" w="612" /><ent r="6" t="8" w="612" /><ent r="6" t="8" w="671" /><ent r="6" t="8" w="671" /><ent r="6" t="8" w="740" /><ent r="6" t="8" w="740" /><ent r="6" t="8" w="819" /><ent r="6" t="8" w="819" /><ent r="6" t="8" w="852" /><ent r="6" t="8" w="852" /><ent r="7" t="71" w="53" /><ent r="7" t="78" w="99" /><ent r="7" t="120" w="36" /><ent r="7" t="120" w="36" /><ent r="7" t="216" w="80" /><ent r="7" t="216" w="80" /><ent r="7" t="232" w="58" /><ent r="7" t="233" w="58" /><ent r="7" t="234" w="58" /><ent r="7" t="235" w="58" /><ent r="7" t="236" w="58" /><ent r="7" t="237" w="61" /><ent r="7" t="238" w="61" /><ent r="7" t="239" w="61" /><ent r="7" t="240" w="61" /><ent r="7" t="241" w="61" /><ent r="7" t="242" w="59" /><ent r="7" t="243" w="59" /><ent r="7" t="244" w="59" /><ent r="7" t="245" w="59" /><ent r="7" t="246" w="59" /><ent r="7" t="265" w="36" /><ent r="7" t="265" w="36" /><ent r="7" t="278" w="34" /><ent r="7" t="278" w="34" /><ent r="7" t="284" w="36" /><ent r="7" t="284" w="36" /><ent r="7" t="289" w="47" /><ent r="7" t="289" w="47" /><ent r="7" t="324" w="39" /><ent r="7" t="324" w="39" /><ent r="7" t="359" w="32" /><ent r="7" t="362" w="25" /><ent r="7" t="367" w="17" /><ent r="7" t="367" w="17" /><ent r="7" t="401" w="18" /><ent r="7" t="402" w="42" /><ent r="7" t="402" w="67" /><ent r="7" t="403" w="25" /><ent r="7" t="405" w="30" /><ent r="7" t="405" w="30" /><ent r="7" t="406" w="18" /><ent r="7" t="406" w="29" /><ent r="7" t="406" w="29" /><ent r="7" t="407" w="24" /><ent r="7" t="407" w="24" /><ent r="7" t="408" w="19" /><ent r="7" t="409" w="22" /><ent r="7" t="409" w="22" /><ent r="7" t="409" w="45" /><ent r="7" t="409" w="45" /><ent r="7" t="410" w="23" /><ent r="7" t="410" w="39" /><ent r="7" t="411" w="17" /><ent r="7" t="411" w="17" /><ent r="7" t="412" w="37" /><ent r="7" t="412" w="51" /><ent r="7" t="412" w="51" /><ent r="7" t="423" w="50" /><ent r="7" t="475" w="11" /><ent r="7" t="475" w="11" /><ent r="7" t="495" w="21" /><ent r="7" t="495" w="21" /><ent r="7" t="501" w="19" /><ent r="7" t="501" w="19" /><ent r="7" t="502" w="34" /><ent r="7" t="503" w="27" /><ent r="7" t="506" w="37" /><ent r="7" t="506" w="37" /><ent r="7" t="515" w="24" /><ent r="7" t="515" w="24" /><ent r="7" t="517" w="20" /><ent r="7" t="517" w="20" /><ent r="7" t="519" w="15" /><ent r="7" t="519" w="32" /><ent r="7" t="519" w="38" /><ent r="7" t="519" w="38" /><ent r="7" t="520" w="22" /><ent r="7" t="522" w="30" /><ent r="7" t="522" w="30" /><ent r="7" t="523" w="38" /><ent r="7" t="523" w="38" /><ent r="7" t="524" w="25" /><ent r="7" t="524" w="25" /><ent r="7" t="525" w="25" /><ent r="7" t="526" w="25" /><ent r="7" t="532" w="44" /><ent r="7" t="551" w="50" /><ent r="7" t="551" w="50" /><ent r="7" t="551" w="67" /><ent r="7" t="551" w="67" /><ent r="7" t="575" w="23" /><ent r="7" t="580" w="11" /><ent r="7" t="580" w="11" /><ent r="7" t="590" w="30" /><ent r="7" t="590" w="30" /><ent r="7" t="591" w="36" /><ent r="7" t="591" w="36" /><ent r="7" t="592" w="19" /><ent r="7" t="592" w="36" /><ent r="7" t="592" w="42" /><ent r="7" t="592" w="42" /><ent r="7" t="593" w="27" /><ent r="7" t="593" w="27" /><ent r="7" t="594" w="28" /><ent r="7" t="594" w="28" /><ent r="7" t="595" w="22" /><ent r="7" t="595" w="53" /><ent r="7" t="596" w="18" /><ent r="7" t="596" w="18" /><ent r="7" t="596" w="45" /><ent r="7" t="596" w="45" /><ent r="7" t="602" w="25" /><ent r="7" t="609" w="14" /><ent r="7" t="609" w="14" /><ent r="7" t="614" w="18" /><ent r="7" t="614" w="18" /><ent r="7" t="614" w="40" /><ent r="7" t="615" w="34" /><ent r="7" t="630" w="34" /><ent r="7" t="630" w="34" /><ent r="7" t="630" w="45" /><ent r="7" t="630" w="45" /><ent r="7" t="630" w="75" /><ent r="7" t="631" w="42" /><ent r="7" t="664" w="16" /><ent r="7" t="664" w="16" /><ent r="7" t="664" w="60" /><ent r="7" t="681" w="47" /><ent r="7" t="681" w="47" /><ent r="7" t="683" w="22" /><ent r="7" t="684" w="17" /><ent r="7" t="684" w="29" /><ent r="7" t="684" w="29" /><ent r="7" t="685" w="18" /><ent r="7" t="686" w="15" /><ent r="7" t="686" w="15" /><ent r="7" t="693" w="18" /><ent r="7" t="693" w="18" /><ent r="7" t="695" w="22" /><ent r="7" t="696" w="21" /><ent r="7" t="696" w="21" /><ent r="7" t="736" w="30" /><ent r="7" t="736" w="30" /><ent r="7" t="737" w="36" /><ent r="7" t="737" w="36" /><ent r="7" t="738" w="19" /><ent r="7" t="738" w="36" /><ent r="7" t="738" w="42" /><ent r="7" t="738" w="42" /><ent r="7" t="739" w="27" /><ent r="7" t="739" w="27" /><ent r="7" t="740" w="28" /><ent r="7" t="740" w="28" /><ent r="7" t="746" w="23" /><ent r="7" t="753" w="16" /><ent r="7" t="764" w="39" /><ent r="7" t="764" w="39" /><ent r="7" t="772" w="18" /><ent r="7" t="772" w="18" /><ent r="7" t="773" w="15" /><ent r="7" t="773" w="15" /><ent r="7" t="784" w="33" /><ent r="7" t="784" w="33" /><ent r="7" t="784" w="44" /><ent r="7" t="784" w="44" /><ent r="7" t="805" w="10" /><ent r="7" t="805" w="10" /><ent r="7" t="864" w="35" /><ent r="7" t="865" w="42" /><ent r="7" t="879" w="11" /><ent r="7" t="937" w="21" /><ent r="7" t="940" w="17" /><ent r="7" t="940" w="17" /><ent r="7" t="942" w="18" /><ent r="7" t="944" w="22" /><ent r="7" t="949" w="21" /><ent r="7" t="950" w="20" /><ent r="7" t="950" w="20" /><ent r="7" t="951" w="19" /><ent r="7" t="951" w="19" /><ent r="7" t="957" w="18" /><ent r="7" t="957" w="31" /><ent r="7" t="958" w="25" /><ent r="7" t="958" w="35" /><ent r="7" t="959" w="18" /><ent r="7" t="959" w="31" /><ent r="7" t="960" w="23" /><ent r="7" t="960" w="33" /><ent r="7" t="961" w="23" /><ent r="7" t="961" w="33" /><ent r="7" t="962" w="30" /><ent r="7" t="962" w="30" /><ent r="7" t="963" w="23" /><ent r="7" t="964" w="22" /><ent r="7" t="964" w="42" /><ent r="7" t="964" w="42" /><ent r="7" t="965" w="22" /><ent r="7" t="965" w="22" /><ent r="7" t="966" w="32" /><ent r="7" t="966" w="32" /><ent r="7" t="967" w="32" /><ent r="7" t="967" w="32" /><ent r="7" t="968" w="32" /><ent r="7" t="968" w="32" /><ent r="7" t="969" w="28" /><ent r="7" t="970" w="28" /><ent r="7" t="971" w="27" /><ent r="7" t="975" w="18" /><ent r="7" t="975" w="18" /><ent r="7" t="985" w="18" /><ent r="7" t="985" w="18" /><ent r="7" t="992" w="24" /><ent r="7" t="996" w="34" /><ent r="7" t="998" w="18" /><ent r="7" t="998" w="18" /><ent r="7" t="1000" w="22" /><ent r="7" t="1002" w="33" /><ent r="7" t="1002" w="33" /><ent r="7" t="1002" w="44" /><ent r="7" t="1002" w="44" /><ent r="7" t="1003" w="20" /><ent r="7" t="1004" w="32" /><ent r="7" t="1005" w="15" /><ent r="7" t="1005" w="42" /><ent r="7" t="1005" w="42" /><ent r="7" t="1006" w="25" /><ent r="7" t="1006" w="25" /><ent r="7" t="1008" w="16" /><ent r="7" t="1009" w="36" /><ent r="7" t="1009" w="36" /><ent r="7" t="1011" w="21" /><ent r="7" t="1012" w="18" /><ent r="7" t="1012" w="18" /><ent r="7" t="1019" w="33" /><ent r="7" t="1019" w="33" /><ent r="7" t="1024" w="19" /><ent r="7" t="1025" w="27" /><ent r="7" t="1027" w="39" /><ent r="7" t="1028" w="18" /><ent r="7" t="1028" w="18" /><ent r="7" t="1033" w="34" /><ent r="7" t="1034" w="18" /><ent r="7" t="1034" w="18" /><ent r="7" t="1044" w="39" /><ent r="7" t="1050" w="43" /><ent r="7" t="1064" w="39" /><ent r="7" t="1069" w="43" /></phr><phr n="Store"><ent r="70" t="5" w="859" /><ent r="70" t="5" w="859" /><ent r="8" t="409" w="15" /><ent r="8" t="409" w="15" /><ent r="7" t="409" w="73" /><ent r="7" t="409" w="73" /><ent r="1000" t="411" w="2" /><ent r="1000" t="411" w="2" /><ent r="106" t="411" w="6" /><ent r="106" t="411" w="6" /><ent r="1000" t="412" w="1" /><ent r="1000" t="412" w="1" /><ent r="106" t="412" w="5" /><ent r="106" t="412" w="5" /><ent r="8" t="412" w="21" /><ent r="8" t="412" w="21" /><ent r="7" t="588" w="28" /><ent r="7" t="588" w="28" /><ent r="1000" t="630" w="3" /><ent r="1000" t="630" w="3" /><ent r="106" t="630" w="7" /><ent r="106" t="630" w="7" /><ent r="7" t="630" w="16" /><ent r="7" t="630" w="16" /><ent r="8" t="630" w="50" /><ent r="8" t="630" w="50" /><ent r="68" t="630" w="82" /><ent r="68" t="630" w="82" /><ent r="1000" t="772" w="3" /><ent r="1000" t="772" w="3" /><ent r="106" t="772" w="8" /><ent r="106" t="772" w="8" /><ent r="1000" t="773" w="2" /><ent r="1000" t="773" w="2" /><ent r="106" t="773" w="6" /><ent r="106" t="773" w="6" /><ent r="1000" t="938" w="1" /><ent r="1000" t="938" w="1" /><ent r="106" t="938" w="5" /><ent r="106" t="938" w="5" /><ent r="1000" t="939" w="1" /><ent r="1000" t="939" w="1" /><ent r="106" t="939" w="4" /><ent r="106" t="939" w="4" /><ent r="1000" t="957" w="2" /><ent r="1000" t="957" w="2" /><ent r="106" t="957" w="7" /><ent r="106" t="957" w="7" /><ent r="1000" t="958" w="2" /><ent r="1000" t="958" w="2" /><ent r="106" t="958" w="8" /><ent r="106" t="958" w="8" /><ent r="1000" t="959" w="2" /><ent r="1000" t="959" w="2" /><ent r="106" t="959" w="7" /><ent r="106" t="959" w="7" /><ent r="1000" t="960" w="2" /><ent r="1000" t="960" w="2" /><ent r="106" t="960" w="7" /><ent r="106" t="960" w="7" /><ent r="1000" t="961" w="2" /><ent r="1000" t="961" w="2" /><ent r="106" t="961" w="7" /><ent r="106" t="961" w="7" /><ent r="1000" t="962" w="2" /><ent r="106" t="962" w="10" /><ent r="1000" t="963" w="2" /><ent r="106" t="963" w="8" /><ent r="1000" t="964" w="2" /><ent r="106" t="964" w="8" /><ent r="1000" t="965" w="2" /><ent r="106" t="965" w="8" /><ent r="1000" t="966" w="2" /><ent r="106" t="966" w="9" /><ent r="8" t="966" w="39" /><ent r="1000" t="967" w="2" /><ent r="106" t="967" w="10" /><ent r="1000" t="968" w="2" /><ent r="106" t="968" w="9" /><ent r="1000" t="969" w="2" /><ent r="106" t="969" w="8" /><ent r="1000" t="970" w="2" /><ent r="106" t="970" w="8" /><ent r="1000" t="971" w="1" /><ent r="1000" t="971" w="1" /><ent r="106" t="971" w="5" /><ent r="106" t="971" w="5" /><ent r="1000" t="1009" w="1" /><ent r="1000" t="1009" w="1" /><ent r="106" t="1009" w="5" /><ent r="106" t="1009" w="5" /><ent r="1000" t="1052" w="2" /><ent r="106" t="1052" w="6" /><ent r="68" t="1081" w="72" /><ent r="68" t="1081" w="215" /><ent r="68" t="1081" w="215" /><ent r="68" t="1081" w="256" /><ent r="68" t="1081" w="256" /><ent r="68" t="1081" w="438" /><ent r="68" t="1081" w="438" /><ent r="68" t="1081" w="666" /><ent r="68" t="1081" w="666" /><ent r="68" t="1081" w="671" /><ent r="68" t="1081" w="671" /><ent r="68" t="1081" w="677" /><ent r="68" t="1081" w="677" /><ent r="68" t="1081" w="682" /><ent r="68" t="1081" w="682" /><ent r="68" t="1081" w="687" /><ent r="68" t="1081" w="687" /><ent r="68" t="1081" w="692" /><ent r="68" t="1081" w="700" /><ent r="68" t="1081" w="706" /><ent r="68" t="1081" w="712" /><ent r="68" t="1081" w="720" /><ent r="68" t="1081" w="727" /><ent r="68" t="1081" w="734" /><ent r="68" t="1081" w="740" /><ent r="68" t="1081" w="746" /><ent r="68" t="1081" w="1450" /><ent r="68" t="1081" w="1450" /><ent r="68" t="1081" w="1454" /><ent r="68" t="1081" w="1454" /><ent r="68" t="1081" w="2089" /><ent r="68" t="1081" w="2089" /><ent r="68" t="1081" w="2093" /><ent r="68" t="1081" w="2093" /><ent r="68" t="1081" w="2574" /><ent r="68" t="1081" w="2574" /><ent r="68" t="1081" w="2577" /><ent r="68" t="1081" w="2577" /></phr><phr n="Stores"><ent r="7" t="336" w="40" /><ent r="7" t="336" w="40" /></phr><phr n="stored"><ent r="7" t="824" w="104" /><ent r="7" t="824" w="104" /><ent r="7" t="992" w="58" /><ent r="7" t="992" w="58" /><ent r="7" t="992" w="90" /><ent r="7" t="992" w="90" /><ent r="3" t="1075" w="62" /><ent r="3" t="1075" w="62" /></phr></stem><stem n="dashboard"><phr n="Dashboard"><ent r="1000" t="2" w="1" /><ent r="1000" t="2" w="1" /><ent r="104" t="2" w="3" /><ent r="104" t="2" w="3" /><ent r="67" t="2" w="10" /><ent r="67" t="2" w="10" /><ent r="8" t="2" w="127" /><ent r="6" t="2" w="169" /><ent r="6" t="2" w="169" /></phr><phr n="dashboard"><ent r="147" t="2" w="21" /><ent r="8" t="2" w="24" /><ent r="8" t="2" w="24" /></phr></stem><stem n="video"><phr n="Video"><ent r="95" t="2" w="5" /><ent r="95" t="2" w="5" /><ent r="7" t="361" w="29" /><ent r="7" t="361" w="29" /><ent r="8" t="361" w="42" /><ent r="8" t="361" w="42" /><ent r="7" t="800" w="69" /><ent r="7" t="800" w="69" /></phr><phr n="Videos"><ent r="95" t="5" w="30" /><ent r="95" t="5" w="30" /><ent r="69" t="5" w="892" /><ent r="69" t="5" w="892" /><ent r="94" t="6" w="5" /><ent r="94" t="6" w="5" /><ent r="95" t="7" w="39" /><ent r="95" t="7" w="39" /></phr><phr n="video"><ent r="7" t="361" w="11" /><ent r="7" t="361" w="11" /><ent r="7" t="361" w="37" /><ent r="7" t="361" w="37" /><ent r="7" t="361" w="70" /><ent r="7" t="361" w="70" /><ent r="7" t="361" w="84" /></phr></stem><stem n="introduct"><phr n="Introduction"><ent r="67" t="2" w="7" /><ent r="67" t="2" w="7" /><ent r="67" t="5" w="32" /><ent r="67" t="5" w="32" /><ent r="67" t="7" w="41" /><ent r="67" t="7" w="41" /></phr></stem><stem n="0m"><phr n="0m"><ent r="67" t="2" w="11" /><ent r="67" t="2" w="11" /><ent r="67" t="5" w="35" /><ent r="67" t="5" w="35" /><ent r="67" t="7" w="47" /><ent r="67" t="7" w="47" /></phr></stem><stem n="28"><phr n="28s"><ent r="67" t="2" w="12" /></phr><phr n="28"><ent r="7" t="89" w="35" /><ent r="7" t="141" w="35" /><ent r="7" t="153" w="35" /><ent r="7" t="394" w="53" /><ent r="7" t="434" w="52" /><ent r="7" t="513" w="42" /><ent r="7" t="587" w="33" /><ent r="7" t="1013" w="35" /><ent r="7" t="1035" w="35" /></phr></stem><stem n="common"><phr n="Common"><ent r="95" t="2" w="14" /><ent r="95" t="2" w="14" /><ent r="95" t="3" w="27" /><ent r="95" t="3" w="27" /><ent r="95" t="5" w="57" /><ent r="95" t="5" w="57" /><ent r="94" t="6" w="26" /><ent r="94" t="6" w="26" /><ent r="95" t="7" w="58" /><ent r="95" t="7" w="58" /></phr><phr n="common"><ent r="6" t="4" w="152" /></phr></stem><stem n="question"><phr n="Questions"><ent r="95" t="2" w="15" /><ent r="95" t="2" w="15" /><ent r="95" t="3" w="28" /><ent r="95" t="3" w="28" /><ent r="95" t="5" w="58" /><ent r="95" t="5" w="58" /><ent r="94" t="6" w="27" /><ent r="94" t="6" w="27" /><ent r="95" t="7" w="59" /><ent r="95" t="7" w="59" /></phr><phr n="Question"><ent r="1000" t="988" w="1" /><ent r="1000" t="988" w="1" /><ent r="106" t="988" w="3" /><ent r="106" t="988" w="3" /><ent r="8" t="988" w="28" /><ent r="8" t="988" w="28" /><ent r="8" t="988" w="34" /><ent r="8" t="988" w="34" /><ent r="9" t="988" w="54" /><ent r="9" t="988" w="54" /><ent r="1000" t="989" w="1" /><ent r="1000" t="989" w="1" /><ent r="106" t="989" w="5" /><ent r="106" t="989" w="5" /><ent r="8" t="989" w="29" /><ent r="8" t="989" w="29" /></phr><phr n="question"><ent r="7" t="988" w="10" /><ent r="7" t="988" w="10" /><ent r="7" t="988" w="45" /></phr></stem><stem n="i"><phr n="I"><ent r="147" t="2" w="18" /><ent r="147" t="2" w="18" /><ent r="147" t="2" w="96" /><ent r="147" t="2" w="96" /><ent r="147" t="3" w="32" /><ent r="147" t="3" w="32" /><ent r="147" t="5" w="62" /><ent r="147" t="5" w="62" /><ent r="147" t="5" w="136" /><ent r="147" t="5" w="136" /><ent r="147" t="5" w="184" /><ent r="147" t="5" w="184" /><ent r="147" t="5" w="276" /><ent r="147" t="5" w="276" /><ent r="147" t="5" w="383" /><ent r="147" t="5" w="383" /><ent r="147" t="5" w="485" /><ent r="147" t="5" w="485" /><ent r="6" t="6" w="31" /><ent r="6" t="6" w="31" /><ent r="6" t="6" w="86" /><ent r="6" t="6" w="86" /><ent r="147" t="7" w="63" /><ent r="147" t="7" w="63" /><ent r="10" t="7" w="133" /><ent r="10" t="7" w="133" /><ent r="147" t="7" w="192" /><ent r="147" t="7" w="192" /><ent r="147" t="7" w="341" /><ent r="147" t="7" w="341" /><ent r="147" t="7" w="446" /><ent r="147" t="7" w="446" /><ent r="8" t="7" w="619" /><ent r="8" t="7" w="619" /></phr><phr n="i"><ent r="1000" t="441" w="6" /><ent r="106" t="441" w="17" /><ent r="7" t="677" w="30" /><ent r="4" t="1082" w="323" /></phr></stem><stem n="my"><phr n="my"><ent r="147" t="2" w="20" /><ent r="147" t="2" w="20" /><ent r="147" t="2" w="98" /><ent r="147" t="2" w="98" /><ent r="147" t="3" w="34" /><ent r="147" t="3" w="34" /><ent r="147" t="3" w="97" /><ent r="147" t="3" w="97" /><ent r="147" t="7" w="198" /><ent r="147" t="7" w="198" /><ent r="8" t="324" w="64" /><ent r="8" t="324" w="64" /><ent r="8" t="409" w="13" /><ent r="8" t="409" w="13" /><ent r="7" t="409" w="71" /><ent r="7" t="409" w="71" /><ent r="8" t="764" w="64" /><ent r="8" t="764" w="64" /><ent r="8" t="824" w="69" /><ent r="8" t="824" w="69" /></phr><phr n="My"><ent r="9" t="2" w="111" /><ent r="9" t="2" w="111" /><ent r="8" t="301" w="17" /><ent r="8" t="301" w="17" /><ent r="8" t="305" w="31" /><ent r="8" t="305" w="31" /><ent r="8" t="319" w="19" /><ent r="8" t="319" w="19" /><ent r="8" t="551" w="30" /><ent r="8" t="551" w="30" /><ent r="8" t="551" w="37" /><ent r="8" t="551" w="37" /><ent r="1000" t="617" w="2" /><ent r="1000" t="617" w="2" /><ent r="106" t="617" w="6" /><ent r="106" t="617" w="6" /><ent r="8" t="623" w="19" /><ent r="8" t="623" w="19" /><ent r="1000" t="669" w="1" /><ent r="1000" t="669" w="1" /><ent r="106" t="669" w="6" /><ent r="106" t="669" w="6" /><ent r="1000" t="670" w="1" /><ent r="1000" t="670" w="1" /><ent r="106" t="670" w="8" /><ent r="106" t="670" w="8" /><ent r="1000" t="671" w="1" /><ent r="1000" t="671" w="1" /><ent r="106" t="671" w="9" /><ent r="106" t="671" w="9" /><ent r="1000" t="672" w="1" /><ent r="1000" t="672" w="1" /><ent r="106" t="672" w="9" /><ent r="106" t="672" w="9" /><ent r="1000" t="673" w="1" /><ent r="1000" t="673" w="1" /><ent r="106" t="673" w="7" /><ent r="106" t="673" w="7" /><ent r="8" t="726" w="17" /><ent r="8" t="726" w="17" /><ent r="8" t="730" w="31" /><ent r="8" t="730" w="31" /><ent r="102" t="1073" w="7" /><ent r="102" t="1073" w="7" /><ent r="68" t="1081" w="546" /><ent r="68" t="1081" w="546" /><ent r="68" t="1081" w="552" /><ent r="68" t="1081" w="552" /><ent r="68" t="1081" w="560" /><ent r="68" t="1081" w="560" /><ent r="68" t="1081" w="565" /><ent r="68" t="1081" w="565" /><ent r="68" t="1081" w="572" /><ent r="68" t="1081" w="572" /></phr></stem></index>